highlighted_pdf_to_anki_flashcards/__init__.py
highlighted_pdf_to_anki_flashcards/cli.py
highlighted_pdf_to_anki_flashcards/extractor.py
highlighted_pdf_to_anki_flashcards/translator_and_generator.py
highlighted_pdf_to_anki_flashcards-0.1.1.dist-info/licenses/LICENSE
highlighted_pdf_to_anki_flashcards-0.1.1.dist-info/METADATA
highlighted_pdf_to_anki_flashcards-0.1.1.dist-info/WHEEL
highlighted_pdf_to_anki_flashcards-0.1.1.dist-info/entry_points.txt
highlighted_pdf_to_anki_flashcards-0.1.1.dist-info/top_level.txt
highlighted_pdf_to_anki_flashcards-0.1.1.dist-info/RECORD
